reqstool_python_hatch_plugin/__init__.py
reqstool_python_hatch_plugin/hooks.py
reqstool_python_hatch_plugin/build_hooks/reqstool.py
reqstool_python_hatch_plugin-0.1.5.dist-info/METADATA
reqstool_python_hatch_plugin-0.1.5.dist-info/WHEEL
reqstool_python_hatch_plugin-0.1.5.dist-info/entry_points.txt
reqstool_python_hatch_plugin-0.1.5.dist-info/licenses/LICENSE
reqstool_python_hatch_plugin-0.1.5.dist-info/RECORD
