Metadata-Version: 2.4
Name: reqstool-python-hatch-plugin
Version: 0.1.5
Summary: Hatch plugin to process reqstool-python-decorators when building with Hatch
Project-URL: Source, https://github.com/Luftfartsverket/reqstool-python-hatch-plugin.git
Author-email: LFV <sysdev@lfv.se>
License-File: LICENSE
Classifier: Development Status :: 4 - Beta
Classifier: License :: OSI Approved :: MIT License
Classifier: Operating System :: OS Independent
Classifier: Programming Language :: Python :: 3
Requires-Python: >=3.10
Requires-Dist: hatchling>=1.20.0
Requires-Dist: reqstool-python-decorators==0.0.9
Requires-Dist: ruamel-yaml==0.19.1
